fastHan/FastCamrModel.py
fastHan/FastModel.py
fastHan/__init__.py
fastHan/model/UserDict.py
fastHan/model/__init__.py
fastHan/model/baseModel.py
fastHan/model/camrModel.py
fastHan/model/camr_finetune_dataloader.py
fastHan/model/camr_restore.py
fastHan/model/camr_to_tuples.py
fastHan/model/dependency_parsing_model.py
fastHan/model/finetune_dataloader.py
fastHan/model/metrics.py
fastHan/model/multitask_metric_base.py
fastHan/model/weight_manager.py
test/__init__.py
test/core/__init__.py
test/core/test_fastHan.py
fastHan-2.0.dist-info/LICENSE
fastHan-2.0.dist-info/METADATA
fastHan-2.0.dist-info/WHEEL
fastHan-2.0.dist-info/top_level.txt
fastHan-2.0.dist-info/RECORD
