Metadata-Version: 2.1
Name: fastHan
Version: 2.0
Summary: 使用深度学习联合模型，解决中文分词、词性标注、命名实体识别、依存分析任务。
Home-page: https://github.com/fastnlp/fastHan
Author: 王鹏宇
License: Apache License
Requires-Python: >=3.6
License-File: LICENSE
